gleif_mcp/__init__.py
gleif_mcp/_gleif_client.py
gleif_mcp/client.py
gleif_mcp/server.py
gleif_mcp_server-0.1.2.dist-info/METADATA
gleif_mcp_server-0.1.2.dist-info/WHEEL
gleif_mcp_server-0.1.2.dist-info/entry_points.txt
gleif_mcp_server-0.1.2.dist-info/licenses/LICENSE
gleif_mcp_server-0.1.2.dist-info/RECORD
