Metadata-Version: 2.4
Name: gleif-mcp-server
Version: 0.1.2
Summary: Model Context Protocol (MCP) server for the GLEIF (Global Legal Entity Identifier Foundation) REST API
Project-URL: Homepage, https://github.com/GenAICPA/gleif-mcp-server
Project-URL: Repository, https://github.com/GenAICPA/gleif-mcp-server
Project-URL: Issues, https://github.com/GenAICPA/gleif-mcp-server/issues
Project-URL: Documentation, https://github.com/GenAICPA/gleif-mcp-server#readme
Author-email: GenAICPA <contact@genacpa.com>
License: Apache-2.0
License-File: LICENSE
Keywords: api,gleif,legal-entity-identifier,lei,mcp,server
Classifier: Development Status :: 4 - Beta
Classifier: Intended Audience :: Developers
Classifier: License :: OSI Approved :: Apache Software License
Classifier: Programming Language :: Python :: 3
Classifier: Programming Language :: Python :: 3.10
Classifier: Programming Language :: Python :: 3.11
Classifier: Programming Language :: Python :: 3.12
Classifier: Topic :: Internet :: WWW/HTTP :: Dynamic Content
Classifier: Topic :: Software Development :: Libraries :: Python Modules
Requires-Python: >=3.10
Requires-Dist: httpx>=0.24.0
Requires-Dist: mcp>=1.0.0
Provides-Extra: dev
Requires-Dist: black>=23.0; extra == 'dev'
Requires-Dist: isort>=5.12.0; extra == 'dev'
Requires-Dist: mypy>=1.0.0; extra == 'dev'
Requires-Dist: pre-commit>=3.0.0; extra == 'dev'
Requires-Dist: pytest-asyncio>=0.21.0; extra == 'dev'
Requires-Dist: pytest>=7.0; extra == 'dev'
Provides-Extra: test
Requires-Dist: httpx>=0.24.0; extra == 'test'
Requires-Dist: pytest-asyncio>=0.21.0; extra == 'test'
Requires-Dist: pytest-cov>=4.0.0; extra == 'test'
Requires-Dist: pytest>=7.0; extra == 'test'
